README.rst
setup.py
collection_filter/__init__.py
collection_filter/collection_filter.py
collection_filter/dict_utils.py
collection_filter.egg-info/PKG-INFO
collection_filter.egg-info/SOURCES.txt
collection_filter.egg-info/dependency_links.txt
collection_filter.egg-info/pbr.json
collection_filter.egg-info/top_level.txt