Metadata-Version: 1.1
Name: collection-filter
Version: 0.5
Summary: A small list/dict DSL for field filter specific designed for RESTful API partial response.
Home-page: https://github.com/kudo/python-collection-filter
Author: Kudo Chien
Author-email: ckchien@gmail.com
License: MIT
Platform: UNKNOWN
Classifier: Development Status :: 3 - Alpha
Classifier: Intended Audience :: Developers
Classifier: License :: OSI Approved :: MIT License
Classifier: Programming Language :: Python :: 2.6
Classifier: Programming Language :: Python :: 2.7
Classifier: Programming Language :: Python :: 3.4
Classifier: Topic :: Software Development :: Libraries :: Python Modules
